pandacell.py
pandacell-2020.9.19.dist-info/METADATA
pandacell-2020.9.19.dist-info/WHEEL
pandacell-2020.9.19.dist-info/top_level.txt
pandacell-2020.9.19.dist-info/RECORD
