Metadata-Version: 2.1
Name: pandacell
Version: 2020.9.19
Summary: IPython wrapper to more easily manipulate Pandas dataframes.
Home-page: https://github.com/eirki/pandacell
Author: Eirik B. Stavestrand
Author-email: eirik.b.stavest@gmail.com
License: MIT
Keywords: pandas
Platform: UNKNOWN
Classifier: Intended Audience :: Developers
Classifier: Environment :: Console
Classifier: License :: OSI Approved :: MIT License
Classifier: Operating System :: OS Independent
Classifier: Programming Language :: Python
Classifier: Programming Language :: Python :: 3.6
Classifier: Programming Language :: Python :: 3 :: Only
Requires-Dist: ipython
